INSTALL.rst
LICENSE
MANIFEST.in
README.rst
VERSION
requirements.txt
setup.py
tasks.py
src/beeswax_api/Exceptions.py
src/beeswax_api/SessionFactory.py
src/beeswax_api/__init__.py
src/beeswax_api/__meta__.py
src/beeswax_api.egg-info/PKG-INFO
src/beeswax_api.egg-info/SOURCES.txt
src/beeswax_api.egg-info/dependency_links.txt
src/beeswax_api.egg-info/not-zip-safe
src/beeswax_api.egg-info/pbr.json
src/beeswax_api.egg-info/top_level.txt
src/beeswax_api/tests/__init__.py
src/beeswax_api/tests/__main__.py
src/beeswax_api/tests/test_beeswax_api.py
src/beeswax_api/tests/test_documentation.py