Metadata-Version: 1.1
Name: beeswax-api
Version: 0.3.0
Summary: Client for the Beeswax API
Home-page: https://github.com/hbmartin/beeswax-api
Author: Harold Martin
Author-email: harold.martin@grindr.com
License: Apache License Version 2.0
Platform: any
Classifier: Development Status :: 3 - Alpha
Classifier: Intended Audience :: Developers
Classifier: Operating System :: OS Independent
Classifier: Programming Language :: Python
Classifier: Programming Language :: Python :: 3
Classifier: Programming Language :: Python :: 3.3
Classifier: Programming Language :: Python :: 3.4
Classifier: Programming Language :: Python :: 3.5
Classifier: Topic :: Software Development :: Libraries
Classifier: License :: OSI Approved :: Apache Software License
